phylofunc/__init__.py
phylofunc/phylofunc.py
phylofunc/data/Taxon_Function_distance.csv
phylofunc/data/Taxon_Function_matrix.csv
phylofunc/data/bac120_iqtree_v2.0.1.nwk
phylofunc-2.0.dist-info/LICENSE.txt
phylofunc-2.0.dist-info/METADATA
phylofunc-2.0.dist-info/WHEEL
phylofunc-2.0.dist-info/top_level.txt
phylofunc-2.0.dist-info/RECORD
