Metadata-Version: 2.1
Name: phylofunc
Version: 2.0
Summary: Generate phylofunc to incorporate microbiome phylogeny to inform on metaproteomic functional distance.
Author: Luman Wang
Author-email: wangluman@bjmu.edu.cn
Classifier: Programming Language :: Python :: 3
Classifier: License :: OSI Approved :: MIT License
Classifier: Operating System :: OS Independent
License-File: LICENSE.txt
Requires-Dist: pandas
Requires-Dist: Bio
